nobita/__init__.py
nobita/greet.py
nobita_nobi-0.1.0.dist-info/METADATA
nobita_nobi-0.1.0.dist-info/WHEEL
nobita_nobi-0.1.0.dist-info/top_level.txt
nobita_nobi-0.1.0.dist-info/RECORD
