Metadata-Version: 2.1
Name: nobita_nobi
Version: 0.1.0
Summary: A Python package that includes Cryptography, Maths, and Telebot modules
Author: samaresh
Classifier: Programming Language :: Python :: 3
Classifier: License :: OSI Approved :: MIT License
Classifier: Operating System :: OS Independent
Requires-Python: >=3.6
